cli.py
build/lib/cli.py
build/lib/commands/__init__.py
build/lib/commands/code.py
build/lib/commands/collect.py
build/lib/commands/commit.py
build/lib/commands/correct.py
build/lib/commands/graph.py
build/lib/commands/pprint.py
build/lib/commands/subl.py
build/lib/commands/tasks.py
build/lib/pnbp/__init__.py
build/lib/pnbp/models.py
build/lib/pnbp/note.py
build/lib/pnbp/notebook.py
build/lib/pnbp/wrappers.py
build/lib/pnbp/helpers/__init__.py
build/lib/pnbp/helpers/base.py
build/lib/pnbp/helpers/codeblock.py
build/lib/pnbp/helpers/link.py
build/lib/pnbp/helpers/tag.py
build/lib/pnbp/helpers/url.py
commands/__init__.py
commands/code.py
commands/collect.py
commands/commit.py
commands/correct.py
commands/graph.py
commands/pprint.py
commands/subl.py
commands/tasks.py
pnbp/__init__.py
pnbp/models.py
pnbp/note.py
pnbp/notebook.py
pnbp/wrappers.py
pnbp/helpers/__init__.py
pnbp/helpers/base.py
pnbp/helpers/codeblock.py
pnbp/helpers/link.py
pnbp/helpers/tag.py
pnbp/helpers/url.py
pnbp-0.8.6.dist-info/LICENSE
pnbp-0.8.6.dist-info/METADATA
pnbp-0.8.6.dist-info/WHEEL
pnbp-0.8.6.dist-info/entry_points.txt
pnbp-0.8.6.dist-info/top_level.txt
pnbp-0.8.6.dist-info/RECORD
